ini/__init__.py
ini/config.py
ini/item.py
ini/section.py
test/__init__.py
test/nullable.py
test/simple.py
ini_klass-0.0.5.dist-info/METADATA
ini_klass-0.0.5.dist-info/WHEEL
ini_klass-0.0.5.dist-info/top_level.txt
ini_klass-0.0.5.dist-info/RECORD
