Metadata-Version: 2.1
Name: ini-klass
Version: 0.0.5
Summary: ini file parser.
Home-page: https://github.com/trk54ylmz/ini-klass
Author: Tarik Yilmaz
Author-email: tarikyilmaz.54@gmail.com
Classifier: Development Status :: 3 - Alpha
Classifier: Operating System :: MacOS
Classifier: Operating System :: Microsoft :: Windows
Classifier: Operating System :: POSIX :: Linux
Classifier: Programming Language :: Python
Classifier: Programming Language :: Python :: 3 :: Only
Classifier: Programming Language :: Python :: 3.7
Classifier: Programming Language :: Python :: 3.8
Classifier: Programming Language :: Python :: 3.9
Classifier: Programming Language :: Python :: 3.10
Requires-Python: >=3.7
